TFIDF_AFSS-1.0.0.dist-info/METADATA
TFIDF_AFSS-1.0.0.dist-info/WHEEL
TFIDF_AFSS/__init__.py
TFIDF_AFSS/TFIDF_AFSS.cp312-win_amd64.pyd
TFIDF_AFSS-1.0.0.dist-info/RECORD
