Metadata-Version: 2.4
Name: TFIDF_AFSS
Version: 1.0.0
Summary: A TFIDF-based Automatic Feature Selection System
Author-email: Benedikt Simbürger <benedikt.simbuerger@edu.htl-klu.at>
License: MIT
Requires-Python: >=3.8
